LICENSE
MANIFEST.in
README.md
clean_repo.sh
conda_env.yml
requirements.txt
setup.py
data/test.arff
data/mcc/chess.mat
data/mcc/madelon.mat
data/mlc/Science1.mat
data/mlc/medical.mat
docfiles/Makefile
docfiles/conf.py
docfiles/core_idea.rst
docfiles/custom_embeddings.rst
docfiles/index.rst
docfiles/installation.rst
docfiles/key_idea.rst
docfiles/make.bat
docfiles/make_all_docs.sh
docfiles/modules.rst
docfiles/reliefe.rst
docfiles/reliefe_types.rst
docfiles/scheme.png
docfiles/task_types.rst
docfiles/_build/doctrees/core_idea.doctree
docfiles/_build/doctrees/custom_embeddings.doctree
docfiles/_build/doctrees/index.doctree
docfiles/_build/doctrees/installation.doctree
docfiles/_build/doctrees/key_idea.doctree
docfiles/_build/doctrees/modules.doctree
docfiles/_build/doctrees/reliefe.doctree
docfiles/_build/doctrees/reliefe_types.doctree
docfiles/_build/doctrees/task_types.doctree
docfiles/_build/doctrees/source/modules.doctree
docfiles/_build/doctrees/source/reliefe.doctree
docfiles/source/modules.rst
docfiles/source/reliefe.rst
docs/.nojekyll
docs/core_idea.html
docs/custom_embeddings.html
docs/genindex.html
docs/index.html
docs/installation.html
docs/key_idea.html
docs/modules.html
docs/objects.inv
docs/py-modindex.html
docs/reliefe.html
docs/reliefe_types.html
docs/search.html
docs/searchindex.js
docs/task_types.html
docs/_images/scheme.png
docs/_sources/core_idea.rst.txt
docs/_sources/custom_embeddings.rst.txt
docs/_sources/index.rst.txt
docs/_sources/installation.rst.txt
docs/_sources/key_idea.rst.txt
docs/_sources/modules.rst.txt
docs/_sources/reliefe.rst.txt
docs/_sources/reliefe_types.rst.txt
docs/_sources/task_types.rst.txt
docs/_sources/source/modules.rst.txt
docs/_sources/source/reliefe.rst.txt
docs/_static/basic.css
docs/_static/doctools.js
docs/_static/documentation_options.js
docs/_static/file.png
docs/_static/jquery-3.5.1.js
docs/_static/jquery.js
docs/_static/language_data.js
docs/_static/minus.png
docs/_static/plus.png
docs/_static/pygments.css
reliefe.egg-info/PKG-INFO
reliefe.egg-info/SOURCES.txt
reliefe.egg-info/dependency_links.txt
reliefe.egg-info/not-zip-safe
reliefe.egg-info/requires.txt
reliefe.egg-info/top_level.txt
